currency/__init__.py
currency/currency.py
currency_tools-1.0.2.dist-info/METADATA
currency_tools-1.0.2.dist-info/WHEEL
currency_tools-1.0.2.dist-info/top_level.txt
currency_tools-1.0.2.dist-info/RECORD
