Metadata-Version: 2.1
Name: currency-tools
Version: 1.0.2
Summary: this method use for who like work with cripto currency
Home-page: https://github.com/jacktamin/cripto_currency
Author: Ahmad Dehghani
Author-email: ahd76money@gmail.com
License: MIT
Keywords: scraping,cripto,bitcoin,currency,api,scrapper,images,videos
Platform: UNKNOWN
Requires-Dist: bs4
Requires-Dist: requests
